learned/__init__.py
learned/metrics/__init__.py
learned/metrics/metrics.py
learned/models/__init__.py
learned/models/models.py
learned/neural_network/__init__.py
learned/neural_network/layers.py
learned/neural_network/models.py
learned/preprocessing/__init__.py
learned/preprocessing/preprocessing.py
learned-0.5.4.5.dist-info/LICENSE
learned-0.5.4.5.dist-info/METADATA
learned-0.5.4.5.dist-info/WHEEL
learned-0.5.4.5.dist-info/top_level.txt
learned-0.5.4.5.dist-info/RECORD
