Metadata-Version: 2.1
Name: learned
Version: 0.5.4.5
Summary: Package containing deep learning model, classic machine learning models, various preprocessing functions and result metrics
Home-page: https://github.com/MERTULAS/learned
Author: H.Mert ULAS
Author-email: h.mert.ulas@gmail.com
License: MIT
Platform: UNKNOWN
Classifier: Intended Audience :: Developers
Classifier: Intended Audience :: Education
Classifier: Intended Audience :: Science/Research
Classifier: License :: OSI Approved :: MIT License
Classifier: Programming Language :: Python :: 3
Classifier: Topic :: Software Development :: Libraries
Classifier: Topic :: Software Development :: Libraries :: Python Modules
Requires-Python: >=3.6.0
Requires-Dist: numpy (>=1.14.0)
